mlx_moe/__init__.py
mlx_moe/generate.py
mlx_moe/loader.py
mlx_moe/phi2moe.py
mlx_moe/qwen2moe.py
mlx_moe-0.0.2.dist-info/METADATA
mlx_moe-0.0.2.dist-info/WHEEL
mlx_moe-0.0.2.dist-info/top_level.txt
mlx_moe-0.0.2.dist-info/RECORD
