Metadata-Version: 2.1
Name: mlx-moe
Version: 0.0.2
Summary: A tool to generate text with mlx-moe model.
Home-page: https://github.com/yourusername/yourproject
Author: Your Name
Author-email: your.email@example.com
License: MIT
Requires-Python: >=3.8
Requires-Dist: mlx >=0.1.0
Requires-Dist: mlx-lm ==0.0.6
